[
  {
    "title": "TGV5IGRlIE9obSAwMQ==",
    "question": "wr9RdcOpIHZhbG9yIHRpZW5lIGxhIGludGVuc2lkYWQgZGUgY29ycmllbnRlPw==",
    "image": "images/0c0071fb195c1e1403c9.png",
    "image_width": 302,
    "choices": [
       "M0E=",
       "MTJB",
       "MC4zM0E=",
       "Ms6p"
    ]
  },
  {
    "title": "TGV5IGRlIE9obSAwMg==",
    "question": "wr9RdcOpIHZhbG9yIHRpZW5lIGxhIGludGVuc2lkYWQgZGUgY29ycmllbnRlPw==",
    "image": "images/a012b2b174e745726c72.png",
    "image_width": 302,
    "choices": [
       "MC4zQQ==",
       "My4zQQ==",
       "MjcwQQ==",
       "OVY="
    ]
  },
  {
    "title": "TGV5IGRlIE9obSAwMw==",
    "question": "wr9RdcOpIHZhbG9yIHRpZW5lIGxhIHRlbnNpw7NuIGRlIGxhIHBpbGE/",
    "image": "images/85f08b1cc1a53ce8e364.png",
    "image_width": 302,
    "choices": [
       "NjBW",
       "MTVW",
       "MC4wNlY=",
       "MkE="
    ]
  },
  {
    "title": "TGV5IGRlIE9obSAwNA==",
    "question": "wr9RdcOpIHZhbG9yIHRpZW5lIGxhIHJlc2lzdGVuY2lhPw==",
    "image": "images/779cc29bdb6063c75fcd.png",
    "image_width": 302,
    "choices": [
       "NjDOqQ==",
       "MTbOqQ==",
       "MC42zqk=",
       "NlY="
    ]
  },
  {
    "title": "TGV5IGRlIE9obSAwNQ==",
    "question": "wr9RdcOpIHZhbG9yIHRpZW5lIGxhIHJlc2lzdGVuY2lhPw==",
    "image": "images/75278c816a0858a29955.png",
    "image_width": 302,
    "choices": [
       "M86p",
       "MjfOqQ==",
       "MC4zM86p",
       "M0E="
    ]
  },
  {
    "title": "TGV5IGRlIE9obSAwNg==",
    "question": "wr9RdcOpIHZhbG9yIHRpZW5lIGxhIHRlbnNpw7NuIGRlIGxhIHBpbGE/",
    "image": "images/2248f71bc2dec821cfc7.png",
    "image_width": 302,
    "choices": [
       "MjRW",
       "Mi42Vg==",
       "MC4zOFY=",
       "OM6p"
    ]
  },
  {
    "title": "TGV5IGRlIE9obSAwNw==",
    "question": "wr9RdcOpIHZhbG9yIHRpZW5lIGxhIGludGVuc2lkYWQgZGUgY29ycmllbnRlPw==",
    "image": "images/8a51f68647c0b3012fb6.png",
    "image_width": 302,
    "choices": [
       "MC4xQQ==",
       "MTBB",
       "MTQ0MEE=",
       "MTIwzqk="
    ]
  },
  {
    "title": "TGV5IGRlIE9obSAwOA==",
    "question": "wr9RdcOpIHZhbG9yIHRpZW5lIGxhIGludGVuc2lkYWQgZGUgY29ycmllbnRlPw==",
    "image": "images/d3adfd0040eb199f5c26.png",
    "image_width": 302,
    "choices": [
       "MS41QQ==",
       "MC42NkE=",
       "MTUwQQ==",
       "MTVW"
    ]
  },
  {
    "title": "TGV5IGRlIE9obSAwOQ==",
    "question": "wr9RdcOpIHZhbG9yIHRpZW5lIGxhIHRlbnNpw7NuIGRlIGxhIHBpbGE/",
    "image": "images/3f4fd893b03af366fc48.png",
    "image_width": 302,
    "choices": [
       "MS41Vg==",
       "MC4wMDZW",
       "MTUwVg==",
       "MC4xQQ=="
    ]
  },
  {
    "title": "TGV5IGRlIE9obSAxMA==",
    "question": "wr9RdcOpIHZhbG9yIHRpZW5lIGxhIHJlc2lzdGVuY2lhPw==",
    "image": "images/49483eb341d3c3d61aef.png",
    "image_width": 302,
    "choices": [
       "MjTOqQ==",
       "Ns6p",
       "MC4wNM6p",
       "MTJW"
    ]
  },
  {
    "title": "TGV5IGRlIE9obSAxMQ==",
    "question": "wr9RdcOpIHZhbG9yIHRpZW5lIGxhIHJlc2lzdGVuY2lhPw==",
    "image": "images/63167f7f0991b9e609ed.png",
    "image_width": 302,
    "choices": [
       "NTAwzqk=",
       "MC40Nc6p",
       "MTXOqQ==",
       "MC4wM0E="
    ]
  },
  {
    "title": "TGV5IGRlIE9obSAxMg==",
    "question": "wr9RdcOpIHZhbG9yIHRpZW5lIGxhIHRlbnNpw7NuIGRlIGxhIHBpbGE/",
    "image": "images/ec7dcfe9af727bcb97bd.png",
    "image_width": 302,
    "choices": [
       "MjBW",
       "NTAwVg==",
       "MC4wMDJW",
       "MTAwzqk="
    ]
  },
  {
    "title": "TGV5IGRlIE9obSAxMw==",
    "question": "wr9RdcOpIHZhbG9yIHRpZW5lIGxhIGludGVuc2lkYWQgZGUgY29ycmllbnRlPw==",
    "image": "images/4beb16ae6481fb66d52c.png",
    "image_width": 302,
    "choices": [
       "MkE=",
       "MC41QQ==",
       "MTYyQQ==",
       "Oc6p"
    ]
  },
  {
    "title": "TGV5IGRlIE9obSAxNA==",
    "question": "wr9RdcOpIHZhbG9yIHRpZW5lIGxhIGludGVuc2lkYWQgZGUgY29ycmllbnRlPw==",
    "image": "images/a64a7c2b70317a56e229.png",
    "image_width": 302,
    "choices": [
       "MC4yNEE=",
       "NC4xNkE=",
       "MjQwMEE=",
       "MjRW"
    ]
  },
  {
    "title": "TGV5IGRlIE9obSAxNQ==",
    "question": "wr9RdcOpIHZhbG9yIHRpZW5lIGxhIHRlbnNpw7NuIGRlIGxhIHBpbGE/",
    "image": "images/2e33a029cd438ec748de.png",
    "image_width": 302,
    "choices": [
       "M1Y=",
       "MTIwMFY=",
       "OFY=",
       "MC4wNUE="
    ]
  },
  {
    "title": "TGV5IGRlIE9obSAxNg==",
    "question": "wr9RdcOpIHZhbG9yIHRpZW5lIGxhIHJlc2lzdGVuY2lhPw==",
    "image": "images/fd9e06a3d8821e71ab56.png",
    "image_width": 302,
    "choices": [
       "Oc6p",
       "MzbOqQ==",
       "MC4xMc6p",
       "MThW"
    ]
  },
  {
    "title": "TGV5IGRlIE9obSAxNw==",
    "question": "wr9RdcOpIHZhbG9yIHRpZW5lIGxhIHJlc2lzdGVuY2lhPw==",
    "image": "images/46491e05e2347a48bb9d.png",
    "image_width": 302,
    "choices": [
       "Ns6p",
       "MC4xNs6p",
       "OTbOqQ==",
       "NEE="
    ]
  },
  {
    "title": "TGV5IGRlIE9obSAxOA==",
    "question": "wr9RdcOpIHZhbG9yIHRpZW5lIGxhIHRlbnNpw7NuIGRlIGxhIHBpbGE/",
    "image": "images/5a9a944b24392b962682.png",
    "image_width": 302,
    "choices": [
       "NVY=",
       "MjBW",
       "MC4wNVY=",
       "MTDOqQ=="
    ]
  },
  {
    "title": "TGV5IGRlIE9obSAyMQ==",
    "question": "wr9RdcOpIHZhbG9yIHRpZW5lIGxhIGludGVuc2lkYWQgZGUgY29ycmllbnRlPw==",
    "image": "images/73879503a0961bb13142.png",
    "image_width": 302,
    "choices": [
       "MS41bUE=",
       "MTVtQQ==",
       "MjRtQQ==",
       "NjY2bUE="
    ]
  },
  {
    "title": "TGV5IGRlIE9obSAyMg==",
    "question": "wr9RdcOpIHZhbG9yIHRpZW5lIGxhIGludGVuc2lkYWQgZGUgY29ycmllbnRlPw==",
    "image": "images/80ad840857510e954bd9.png",
    "image_width": 302,
    "choices": [
       "MC42bUE=",
       "MC4wNm1B",
       "MTM1bUE=",
       "MTY2Nm1B"
    ]
  },
  {
    "title": "TGV5IGRlIE9obSAyMw==",
    "question": "wr9RdcOpIHZhbG9yIHRpZW5lIGxhIHRlbnNpw7NuIGRlIGxhIHBpbGE/",
    "image": "images/78faa2ad4eb1c4660227.png",
    "image_width": 302,
    "choices": [
       "MTAwVg==",
       "MjVW",
       "MC4wNFY=",
       "MTAwMDAwVg=="
    ]
  },
  {
    "title": "TGV5IGRlIE9obSAyNA==",
    "question": "wr9RdcOpIHZhbG9yIHRpZW5lIGxhIHJlc2lzdGVuY2lhPw==",
    "image": "images/4114bba786e92f7fe156.png",
    "image_width": 302,
    "choices": [
       "MzBrzqk=",
       "M2vOqQ==",
       "MS4ya86p",
       "MzPOqQ=="
    ]
  },
  {
    "title": "TGV5IGRlIE9obSAyNQ==",
    "question": "wr9RdcOpIHZhbG9yIHRpZW5lIGxhIHJlc2lzdGVuY2lhPw==",
    "image": "images/401b669e8faf46d1216a.png",
    "image_width": 302,
    "choices": [
       "MS41a86p",
       "MTVrzqk=",
       "MC42NjZrzqk=",
       "MS41zqk="
    ]
  },
  {
    "title": "TGV5IGRlIE9obSAyNg==",
    "question": "wr9RdcOpIHZhbG9yIHRpZW5lIGxhIHRlbnNpw7NuIGRlIGxhIHBpbGE/",
    "image": "images/a35d90212c65e5e74382.png",
    "image_width": 302,
    "choices": [
       "NjBW",
       "NjAwMDBW",
       "MTY2NlY=",
       "MC42Vg=="
    ]
  },
  {
    "title": "TGV5IGRlIE9obSAyNw==",
    "question": "wr9RdcOpIHZhbG9yIHRpZW5lIGxhIGludGVuc2lkYWQgZGUgY29ycmllbnRlPw==",
    "image": "images/bf4f53704aaa168ba941.png",
    "image_width": 302,
    "choices": [
       "MC4ybUE=",
       "Mm1B",
       "NW1B",
       "MC41bUE="
    ]
  },
  {
    "title": "TGV5IGRlIE9obSAyOA==",
    "question": "wr9RdcOpIHZhbG9yIHRpZW5lIGxhIGludGVuc2lkYWQgZGUgY29ycmllbnRlPw==",
    "image": "images/728cfb0d391cee15598d.png",
    "image_width": 302,
    "choices": [
       "M21B",
       "M0E=",
       "NzVtQQ==",
       "MC4zMzNtQQ=="
    ]
  },
  {
    "title": "TGV5IGRlIE9obSAyOQ==",
    "question": "wr9RdcOpIHZhbG9yIHRpZW5lIGxhIHRlbnNpw7NuIGRlIGxhIHBpbGE/",
    "image": "images/72363df19a362ec2ed55.png",
    "image_width": 302,
    "choices": [
       "M1Y=",
       "M21W",
       "NzVW",
       "MzBW"
    ]
  },
  {
    "title": "TGV5IGRlIE9obSAzMA==",
    "question": "wr9RdcOpIHZhbG9yIHRpZW5lIGxhIHJlc2lzdGVuY2lhPw==",
    "image": "images/c48ba387de5e540de7a7.png",
    "image_width": 302,
    "choices": [
       "MzBrzqk=",
       "M2vOqQ==",
       "NC44a86p",
       "MzNrzqk="
    ]
  },
  {
    "title": "TGV5IGRlIE9obSAzMQ==",
    "question": "wr9RdcOpIHZhbG9yIHRpZW5lIGxhIHJlc2lzdGVuY2lhPw==",
    "image": "images/103cd2fb428835b1f03a.png",
    "image_width": 302,
    "choices": [
       "MzAwa86p",
       "MzBrzqk=",
       "M2vOqQ==",
       "MC43NWvOqQ=="
    ]
  },
  {
    "title": "TGV5IGRlIE9obSAzMg==",
    "question": "wr9RdcOpIHZhbG9yIHRpZW5lIGxhIHRlbnNpw7NuIGRlIGxhIHBpbGE/",
    "image": "images/07864a35babbed0fb881.png",
    "image_width": 302,
    "choices": [
       "MzZW",
       "MzYwVg==",
       "My42Vg==",
       "NDAwVg=="
    ]
  },
  {
    "title": "TGV5IGRlIE9obSAzMw==",
    "question": "wr9RdcOpIHZhbG9yIHRpZW5lIGxhIGludGVuc2lkYWQgZGUgY29ycmllbnRlPw==",
    "image": "images/08148e3412fb5a260357.png",
    "image_width": 302,
    "choices": [
       "M21B",
       "MC4zbUE=",
       "MC4zMzNtQQ==",
       "MTA4bUE="
    ]
  },
  {
    "title": "TGV5IGRlIE9obSAzNA==",
    "question": "wr9RdcOpIHZhbG9yIHRpZW5lIGxhIGludGVuc2lkYWQgZGUgY29ycmllbnRlPw==",
    "image": "images/4e35a2b65b03364ea2f4.png",
    "image_width": 302,
    "choices": [
       "MC40OG1B",
       "NC44bUE=",
       "Mi4wOG1B",
       "MTIwMG1B"
    ]
  },
  {
    "title": "TGV5IGRlIE9obSAzNQ==",
    "question": "wr9RdcOpIHZhbG9yIHRpZW5lIGxhIHRlbnNpw7NuIGRlIGxhIHBpbGE/",
    "image": "images/c8ed950acb5b6341b3b7.png",
    "image_width": 302,
    "choices": [
       "MjBW",
       "MlY=",
       "MzIwVg==",
       "MC4wMDNW"
    ]
  },
  {
    "title": "TGV5IGRlIE9obSAzNg==",
    "question": "wr9RdcOpIHZhbG9yIHRpZW5lIGxhIHJlc2lzdGVuY2lhPw==",
    "image": "images/8b39dd1ac0080733b5e6.png",
    "image_width": 302,
    "choices": [
       "NmvOqQ==",
       "NjBrzqk=",
       "MC4xNjZrzqk=",
       "NTRrzqk="
    ]
  },
  {
    "title": "TGV5IGRlIE9obSAzNw==",
    "question": "wr9RdcOpIHZhbG9yIHRpZW5lIGxhIHJlc2lzdGVuY2lhPw==",
    "image": "images/4a3439e7a1dc89aaf367.png",
    "image_width": 302,
    "choices": [
       "M2vOqQ==",
       "MzBrzqk=",
       "MTkya86p",
       "MC4zMzNrzqk="
    ]
  },
  {
    "title": "TGV5IGRlIE9obSAzOA==",
    "question": "wr9RdcOpIHZhbG9yIHRpZW5lIGxhIHRlbnNpw7NuIGRlIGxhIHBpbGE/",
    "image": "images/161598c417e769d7fa10.png",
    "image_width": 302,
    "choices": [
       "NlY=",
       "NjAwMFY=",
       "MzcuNVY=",
       "MC4wMjZW"
    ]
  }
]